wavejax/LICENSE
wavejax/README.md
wavejax/__init__.py
wavejax/clustering.py
wavejax/constants.py
wavejax-0.0.3.dist-info/METADATA
wavejax-0.0.3.dist-info/WHEEL
wavejax-0.0.3.dist-info/RECORD
